ctinexus/__init__.py
ctinexus/app.py
ctinexus/cti_processor.py
ctinexus/graph_constructor.py
ctinexus/llm_processor.py
ctinexus/config/config.yaml
ctinexus/config/cost.json
ctinexus/data/annotation/0-days-exploited-by-commercial-surveillance-vendor-in-egypt.json
ctinexus/data/annotation/3am-ransomware-lockbit.json
ctinexus/data/annotation/active-north-korean-campaign-targeting-security-researchers.json
ctinexus/data/annotation/agonizing-serpens-targets-israeli-tech-higher-ed-sectors.json
ctinexus/data/annotation/amd-apple-qualcomm-gpus-leak-ai-data-in-leftoverlocals-attacks.json
ctinexus/data/annotation/an-in-depth-look-at-cuba-ransomware.json
ctinexus/data/annotation/an-in-depth-look-at-quantum-ransomware.json
ctinexus/data/annotation/an-in-depth-look-at-rhysida-ransomware.json
ctinexus/data/annotation/apache-erp-0day-underscores-dangers-of-incomplete-patches.json
ctinexus/data/annotation/apple-fixes-first-zero-day-bug-exploited-in-attacks-this-year.json
ctinexus/data/annotation/apt-lazarus-macos-malware.json
ctinexus/data/annotation/apts-swarm-zimbra-zero-day-to-steal-government-info-worldwide.json
ctinexus/data/annotation/attackers-exploit-microsoft-office-bug-spyware.json
ctinexus/data/annotation/attackers-target-max-severity-apache-activemq-bug-to-drop-ransomware.json
ctinexus/data/annotation/black-basta-bl00dy-ransomware-exploiting-recent-screenconnect-flaws.json
ctinexus/data/annotation/blackcat-ransomware-releases-new-utility-munchkin.json
ctinexus/data/annotation/buckeye-windows-zero-day-exploit.json
ctinexus/data/annotation/budworm-tool-update-telecoms-govt.json
ctinexus/data/annotation/cadet-blizzard-emerges-as-a-novel-and-distinct-russian-threat-actor.json
ctinexus/data/annotation/chinese-hackers-exploit-vmware-bug-as-zero-day-for-two-years.json
ctinexus/data/annotation/chinese-hackers-exploited-new-zero-day.json
ctinexus/data/annotation/chrome-update-patches-zero-day-vulnerabilities-exploited-at-pwn2own.json
ctinexus-0.1.0.dist-info/licenses/LICENSE.txt
ctinexus-0.1.0.dist-info/METADATA
ctinexus-0.1.0.dist-info/WHEEL
ctinexus-0.1.0.dist-info/entry_points.txt
ctinexus-0.1.0.dist-info/top_level.txt
ctinexus-0.1.0.dist-info/RECORD
