Metadata-Version: 2.4
Name: ctinexus
Version: 0.1.0
Summary: CTINexus: A framework for data-efficient cyber threat intelligence extraction and knowledge graph construction using LLMs.
Author-email: Saimon Tsegai <49simoney@gmail.com>, Yutong Cheng <yutongcheng@vt.edu>
License: The MIT License
Project-URL: Repository, https://github.com/peng-gao-lab/CTINexus
Project-URL: Homepage, https://ctinexus.github.io
Classifier: Programming Language :: Python :: 3
Classifier: Programming Language :: Python :: 3.10
Classifier: Programming Language :: Python :: 3.11
Classifier: Programming Language :: Python :: 3.12
Classifier: License :: OSI Approved :: MIT License
Classifier: Topic :: Security
Classifier: Topic :: Scientific/Engineering :: Artificial Intelligence
Requires-Python: >=3.10
License-File: LICENSE.txt
Requires-Dist: gradio
Requires-Dist: hydra-core
Requires-Dist: jinja2
Requires-Dist: litellm
Requires-Dist: networkx
Requires-Dist: nltk
Requires-Dist: omegaconf
Requires-Dist: pandas
Requires-Dist: pyvis
Requires-Dist: python-dotenv
Requires-Dist: scikit-learn
Requires-Dist: scipy
Provides-Extra: dev
Requires-Dist: ruff>=0.8.0; extra == "dev"
Requires-Dist: pre-commit>=4.0.0; extra == "dev"
Dynamic: license-file
